controllable/__init__.py
controllable/Analyse/__init__.py
controllable/Analyse/Data/__init__.py
controllable/Analyse/Data/Database/__init__.py
controllable/Analyse/Data/Database/database_utils.py
controllable/Analyse/Data/Types/__init__.py
controllable/Analyse/Data/Types/circuit_datatype.py
controllable/Analyse/Data/Types/eis_datatype.py
controllable/Analyse/Data/Types/eis_test_circuits.yaml
controllable/Analyse/Data/Types/eis_tests.json
controllable/Analyse/Visualisation/__init__.py
controllable/Analyse/Visualisation/visualisation_utils.py
controllable/Compound/__init__.py
controllable/Compound/LiquidMover/__init__.py
controllable/Compound/LiquidMover/liquidmover_utils.py
controllable/Compound/LiquidMover/Opentrons/__init__.py
controllable/Compound/LiquidMover/Opentrons/opentrons_utils.py
controllable/Control/__init__.py
controllable/Control/GUI/__init__.py
controllable/Control/GUI/_guibuilder.py
controllable/Control/GUI/basic_panels.py
controllable/Control/GUI/gui_utils.py
controllable/Control/Schedule/__init__.py
controllable/Control/Schedule/schedule_utils.py
controllable/Make/__init__.py
controllable/Make/Mixture/__init__.py
controllable/Make/ThinFilm/__init__.py
controllable/Make/ThinFilm/spinner_utils.py
controllable/Measure/__init__.py
controllable/Measure/Electrical/__init__.py
controllable/Measure/Electrical/electrical_utils.py
controllable/Measure/Electrical/Keithley/__init__.py
controllable/Measure/Electrical/Keithley/keithley_device.py
controllable/Measure/Electrical/Keithley/keithley_utils.py
controllable/Measure/Electrical/Keithley/programs/__init__.py
controllable/Measure/Electrical/Keithley/programs/base_programs.py
controllable/Measure/Mechanical/__init__.py
controllable/Measure/Mechanical/PiezoRobotics/__init__.py
controllable/Measure/Mechanical/PiezoRobotics/piezorobotics_device.py
controllable/Measure/Mechanical/PiezoRobotics/piezorobotics_lib.py
controllable/Measure/Mechanical/PiezoRobotics/piezorobotics_utils.py
control_lab_les-0.0.0.5.dist-info/LICENSE
control_lab_les-0.0.0.5.dist-info/METADATA
control_lab_les-0.0.0.5.dist-info/WHEEL
control_lab_les-0.0.0.5.dist-info/top_level.txt
control_lab_les-0.0.0.5.dist-info/RECORD
