Metadata-Version: 2.1
Name: control-lab-les
Version: 0.0.0.5
Summary: Lab Equipment Automation Package
Home-page: https://github.com/kylejeanlewis/control-lab-le
Author: Chang Jie Leong
Author-email: <changjie.leong@outlook.com>
License: MIT
Keywords: python,lab automation
Platform: UNKNOWN
Classifier: Development Status :: 1 - Planning
Classifier: Intended Audience :: Developers
Classifier: Programming Language :: Python :: 3
Classifier: Programming Language :: Python :: 3.7
Classifier: Programming Language :: Python :: 3.8
Classifier: Operating System :: Microsoft :: Windows
Classifier: License :: OSI Approved :: MIT License
Requires-Dist: dash (>=2.7)
Requires-Dist: impedance (>=1.4)
Requires-Dist: imutils (>=0.5)
Requires-Dist: matplotlib (>=3.3)
Requires-Dist: nest-asyncio (>=1.5)
Requires-Dist: numpy (>=1.19)
Requires-Dist: opencv-python (>=4.5.0)
Requires-Dist: pandas (>=1.2)
Requires-Dist: plotly (>=5.3)
Requires-Dist: pyModbusTCP (>=0.2)
Requires-Dist: pyserial (>=3.5)
Requires-Dist: PySimpleGUI
Requires-Dist: PyVISA (>=1.12)
Requires-Dist: PyYAML
Requires-Dist: scipy (>=1.6)
